LICENSE
README.md
setup.py
ps2mqtt/__init__.py
ps2mqtt/daemon.py
ps2mqtt.egg-info/PKG-INFO
ps2mqtt.egg-info/SOURCES.txt
ps2mqtt.egg-info/dependency_links.txt
ps2mqtt.egg-info/entry_points.txt
ps2mqtt.egg-info/requires.txt
ps2mqtt.egg-info/top_level.txt