Metadata-Version: 2.4
Name: ps2mqtt
Version: 0.0.8
Summary: Python daemon that gets information from psutil to an mqtt broker for integration with Home Assistant.
Home-page: https://github.com/dgomes/ps2mqtt
Author: Diogo Gomes
Author-email: diogogomes@gmail.com
Classifier: Programming Language :: Python :: 3.0
Classifier: Topic :: Utilities
Classifier: Environment :: No Input/Output (Daemon)
Classifier: Operating System :: POSIX
Classifier: Intended Audience :: System Administrators
License-File: LICENSE
Requires-Dist: setuptools==78.1.1
Requires-Dist: paho-mqtt>=1.6.1
Requires-Dist: python-slugify>=6.1.1
Requires-Dist: psutil==5.9.5
Requires-Dist: PyYAML==6.0.1
Dynamic: author
Dynamic: author-email
Dynamic: classifier
Dynamic: description
Dynamic: description-content-type
Dynamic: home-page
Dynamic: license-file
Dynamic: requires-dist
Dynamic: summary
